contextual_privacy_llm/__init__.py
contextual_privacy_llm/analyzer.py
contextual_privacy_llm/runner.py
contextual_privacy_llm/patterns/__init__.py
contextual_privacy_llm/patterns/intent_patterns.py
contextual_privacy_llm/patterns/task_patterns.py
contextual_privacy_llm/prompts/deepseek/essential_info.txt
contextual_privacy_llm/prompts/deepseek/essential_info_static.txt
contextual_privacy_llm/prompts/deepseek/intent_detection.txt
contextual_privacy_llm/prompts/deepseek/non_essential_info.txt
contextual_privacy_llm/prompts/deepseek/non_essential_info_static.txt
contextual_privacy_llm/prompts/deepseek/reformulation.txt
contextual_privacy_llm/prompts/deepseek/sensitive_info.txt
contextual_privacy_llm/prompts/deepseek/task_detection.txt
contextual_privacy_llm/prompts/llama/essential_info.txt
contextual_privacy_llm/prompts/llama/essential_info_static.txt
contextual_privacy_llm/prompts/llama/intent_detection.txt
contextual_privacy_llm/prompts/llama/non_essential_info.txt
contextual_privacy_llm/prompts/llama/non_essential_info_static.txt
contextual_privacy_llm/prompts/llama/reformulation.txt
contextual_privacy_llm/prompts/llama/sensitive_info.txt
contextual_privacy_llm/prompts/llama/task_detection.txt
contextual_privacy_llm/prompts/mixtral/essential_info.txt
contextual_privacy_llm/prompts/mixtral/essential_info_static.txt
contextual_privacy_llm/prompts/mixtral/intent_detection.txt
contextual_privacy_llm/prompts/mixtral/non_essential_info.txt
contextual_privacy_llm/prompts/mixtral/non_essential_info_static.txt
contextual_privacy_llm/prompts/mixtral/reformulation.txt
contextual_privacy_llm/prompts/mixtral/sensitive_info.txt
contextual_privacy_llm/prompts/mixtral/task_detection.txt
contextual_privacy_llm-0.1.8.dist-info/licenses/LICENSE
contextual_privacy_llm-0.1.8.dist-info/METADATA
contextual_privacy_llm-0.1.8.dist-info/WHEEL
contextual_privacy_llm-0.1.8.dist-info/entry_points.txt
contextual_privacy_llm-0.1.8.dist-info/top_level.txt
contextual_privacy_llm-0.1.8.dist-info/RECORD
